lib4P/__init__.py
lib4P/naming_convention.py
lib4P/verbose.py
lib4P/argparse/__init__.py
lib4P/argparse/explicit_boolean_action.py
lib4P/datasets/__init__.py
lib4P/datasets/dataset_provider_interface.py
lib4P/datasets/nextcloud_dataset_provider.py
lib4P/logging/__init__.py
lib4P/metadata/__init__.py
lib4P/metadata/data.py
lib4P/metadata/geolocation.py
lib4P/metadata/metadata.py
lib4P/metadata/plot.py
lib4P/metadata/position.py
lib4P/metadata/sensor.py
lib4P/metadata/session.py
lib4P/metadata/utils.py
lib4P/metadata/vector.py
lib4P/metadata/abstract/__init__.py
lib4P/metadata/abstract/abstract_additional_attributes.py
lib4P/metadata/abstract/abstract_data_linker.py
lib4P/metadata/abstract/abstract_geolocation_linker.py
lib4P/metadata/abstract/abstract_metadata_linker.py
lib4P/metadata/abstract/abstract_plot_linker.py
lib4P/metadata/abstract/abstract_sensor_linker.py
lib4P/metadata/adapter/__init__.py
lib4P/metadata/adapter/image_metadata/__init__.py
lib4P/metadata/adapter/image_metadata/camera_sensor.py
lib4P/metadata/adapter/image_metadata/image.py
lib4P/metadata/adapter/image_metadata/plot.py
lib4P/metadata/adapter/image_metadata/interface/__init__.py
lib4P/metadata/adapter/image_metadata/interface/image_interface.py
lib4P/metadata/adapter/image_metadata/interface/image_linker_interface.py
lib4P/metadata/adapter/image_metadata/parser/__init__.py
lib4P/metadata/adapter/image_metadata/parser/camera_sensor/__init__.py
lib4P/metadata/adapter/image_metadata/parser/camera_sensor/v0_0_0.py
lib4P/metadata/adapter/image_metadata/parser/camera_sensor/v1_0_0.py
lib4P/metadata/adapter/image_metadata/parser/image/__init__.py
lib4P/metadata/adapter/image_metadata/parser/image/v0_0_0.py
lib4P/metadata/adapter/image_metadata/parser/image/v1_0_0.py
lib4P/metadata/adapter/image_metadata/parser/plot/__init__.py
lib4P/metadata/adapter/image_metadata/parser/plot/v0_0_0.py
lib4P/metadata/adapter/lidar_metadata/__init__.py
lib4P/metadata/adapter/mspec_metadata/__init__.py
lib4p-1.0.0.dist-info/licenses/LICENSE.txt
lib4p-1.0.0.dist-info/METADATA
lib4p-1.0.0.dist-info/WHEEL
lib4p-1.0.0.dist-info/top_level.txt
lib4p-1.0.0.dist-info/RECORD
